file_downloader/__init__.py
file_downloader/__main__.py
file_downloader/constants.py
file_downloader/downloader.py
file_downloader/downloader_hyper.py
python_file_downloader-1.0.0.dist-info/DESCRIPTION.rst
python_file_downloader-1.0.0.dist-info/METADATA
python_file_downloader-1.0.0.dist-info/RECORD
python_file_downloader-1.0.0.dist-info/WHEEL
python_file_downloader-1.0.0.dist-info/entry_points.txt
python_file_downloader-1.0.0.dist-info/metadata.json
python_file_downloader-1.0.0.dist-info/top_level.txt
src/file_downloader/__init__.py
src/file_downloader/__main__.py
src/file_downloader/constants.py
src/file_downloader/downloader.py
src/file_downloader/downloader_hyper.py
