Metadata-Version: 2.0
Name: python-file-downloader
Version: 1.0.0
Summary: python ag test
Home-page: http://graphai.co
Author: Marti Bayo Alemany
Author-email: martibayoalemany@gmail.com
License: MIT
Platform: UNKNOWN
Requires-Dist: asyncio (==3.4.3)
Requires-Dist: autopep8 (==1.3.2)
Requires-Dist: BeautifulSoup (==3.2.1)
Requires-Dist: beautifulsoup4 (==4.6.0)
Requires-Dist: bs4 (==0.0.1)
Requires-Dist: enum34 (==1.1.6)
Requires-Dist: h2 (==2.6.2)
Requires-Dist: hpack (==3.0.0)
Requires-Dist: html5lib (==0.999999999)
Requires-Dist: hyper (==0.7.0)
Requires-Dist: hyperframe (==3.2.0)
Requires-Dist: mechanize (==0.3.3)
Requires-Dist: pkg-resources (==0.0.0)
Requires-Dist: pycodestyle (==2.3.1)
Requires-Dist: six (==1.10.0)
Requires-Dist: webencodings (==0.5.1)
